MANIFEST.in
setup.py
django_live.egg-info/PKG-INFO
django_live.egg-info/SOURCES.txt
django_live.egg-info/dependency_links.txt
django_live.egg-info/not-zip-safe
django_live.egg-info/top_level.txt
live/COPYING.txt
live/README.txt
live/__init__.py
live/settings.py
live/urls.py
live/views.py
live/templates/live/chat.html
live/templates/live/manage.html