Metadata-Version: 1.0
Name: django-live
Version: 0.1.8
Summary: Comet based chat for django. Similar to humanclick / livephp. Also public rooms
Home-page: http://bitbucket.org/nicoechaniz/django-live/
Author: nicoechaniz
Author-email: nico@rakar.com
License: UNKNOWN
Platform: UNKNOWN
